[{"id":1,"specialist":"lyheang","latlng":"11.564404530398207,104.92460520629884","seftDescription":"I want to help people","category":"IT","contact":{"telegram":"https://telegram/123","linkedIn":"https://LinkedIn/123","line":"https://LinkedIn/123"},"image":["https://res.cloudinary.com/dtlftd49k/image/upload/v1675411677/PROJECT/ejb5tov1gfluov4yjmyb.jpg"],"location":"Koh Kong","profession":"Software engineer","phoneContact":"0109873547","background":"ljslkfjsw","relatedWork":["https://res.cloudinary.com/dtlftd49k/image/upload/v1675411678/PROJECT/ddvptkof5qwqyumziqej.png","https://res.cloudinary.com/dtlftd49k/image/upload/v1675411678/PROJECT/zapznw0wt9q9msdn2ihj.png","https://res.cloudinary.com/dtlftd49k/image/upload/v1675411678/PROJECT/oouqjxdkkmkchyoznw8c.png"]},{"id":2,"specialist":"Suli","latlng":"11.565351990289956,104.92349839006401","seftDescription":"I love design","category":"Graphic-Designer","contact":{"telegram":"https://telegram/123","linkedIn":"https://LinkedIn/123","line":"https://LinkedIn/34"},"image":["https://res.cloudinary.com/dtlftd49k/image/upload/v1675411900/PROJECT/k6x3fqwry1ftspclyuav.jpg"],"location":"Banteay Meanchey","profession":"Interior Designer","phoneContact":"01928374","background":"klslkflksdflksj","relatedWork":["https://res.cloudinary.com/dtlftd49k/image/upload/v1675411901/PROJECT/uilij77bbjqngzj6niz2.png","https://res.cloudinary.com/dtlftd49k/image/upload/v1675411901/PROJECT/miwh8iqymjsfz1bsc8lc.png"]},{"specialist":"Kris","latlng":"undefined","category":"IT","contact":{"telegram":"https://telegram/123","line":"https://LinkedIn/123"},"image":["https://res.cloudinary.com/dtlftd49k/image/upload/v1675435620/PROJECT/cntqrbrlnhwisxjmevkj.jpg"],"location":"Koh Kong","profession":"Civil engineer","phoneContact":"0109873547","background":"I love pc","profile":null,"relatedWork":[],"password":"23","service":null,"email":"susu@gmail.com"},{"id":null,"specialist":"Lucy","latlng":"11.56469883937733,104.92155821685792","seftDescription":"I like doing with building","category":"Architect","contact":{"telegram":"teltegram","linkedIn":"lmao@gmail.com","line":"Brosith@gmail.com"},"image":[],"location":"Kampot","profession":"Mechanical Engineering","phoneContact":"awdawda","background":"lkkllk","email":null,"password":null,"company":null,"relatedWork":["https://res.cloudinary.com/dtlftd49k/image/upload/v1675473001/PROJECT/snuhlorudpymm7iguizf.png"]},{"specialist":"Brosith","latlng":"undefined","category":"Engineer","contact":{"telegram":"Brosith","line":"lmao@gmail.com"},"image":["https://res.cloudinary.com/dtlftd49k/image/upload/v1675476016/PROJECT/z3xq3sjptvvzfshdewiu.png"],"location":"Phnom Penh","profession":"Mechanical Engineering","phoneContact":"0168168","background":"Engineering","profile":null,"relatedWork":["https://res.cloudinary.com/dtlftd49k/image/upload/v1675476142/PROJECT/stnosrt7ejpsuch4wtfe.png"],"password":"123456789","service":null,"email":"Brosith@gmail.com"},{"id":null,"specialist":"lyheang","latlng":"11.555659208175475,104.92662222747803","seftDescription":"hi","category":"Electrician","contact":{"telegram":"awdada","linkedIn":"awdada","line":"wada"},"image":["https://res.cloudinary.com/dtlftd49k/image/upload/v1675476631/PROJECT/doh4usbed8m20ya8kutm.png"],"location":"Phnom Penh","profession":"Mechanical Engineering","phoneContact":"11111111","background":"ur life","email":null,"password":null,"company":null,"relatedWork":["https://res.cloudinary.com/dtlftd49k/image/upload/v1675476631/PROJECT/aifx3ywnkfvg7rwocwuv.png"]}]